landslide/__init__.py
landslide/__main__.py
landslide/generator.py
landslide/macro.py
landslide/main.py
landslide/parser.py
landslide/rst.py
landslide/utils.py
landslide/watcher.py
landslide/themes/default/base.html
landslide/themes/default/css/print.css
landslide/themes/default/css/screen.css
landslide/themes/default/js/slides.js
landslide/themes/leapmotion/base.html
landslide/themes/leapmotion/css/print.css
landslide/themes/leapmotion/css/screen.css
landslide/themes/leapmotion/js/slides.js
landslide/themes/light/css/screen.css
landslide/themes/ribbon/base.html
landslide/themes/ribbon/license.txt
landslide/themes/ribbon/css/defaults.scss
landslide/themes/ribbon/css/print.css
landslide/themes/ribbon/css/print.scss
landslide/themes/ribbon/css/reset.scss
landslide/themes/ribbon/css/screen.css
landslide/themes/ribbon/css/screen.scss
landslide/themes/ribbon/images/grid-16x10.png
landslide/themes/ribbon/images/grid-4x3.png
landslide/themes/ribbon/images/linen.png
landslide/themes/ribbon/images/ribbon.svg
landslide/themes/ribbon/js/slides.js
landslide/themes/tango/css/background.png
landslide/themes/tango/css/screen.css
landslide-1.1.9.dist-info/LICENSE
landslide-1.1.9.dist-info/METADATA
landslide-1.1.9.dist-info/WHEEL
landslide-1.1.9.dist-info/entry_points.txt
landslide-1.1.9.dist-info/top_level.txt
landslide-1.1.9.dist-info/RECORD
