Metadata-Version: 2.1
Name: landslide
Version: 1.1.9
Summary: HTML5 slideshow generator for Markdown, ReST, and Textile
Home-page: http://github.com/adamzap/landslide
Author: Adam Zapletal
Author-email: adamzap@gmail.com
License: Apache 2.0
Keywords: markdown,slideshow,presentation,rst,restructuredtext,textile
Platform: any
Classifier: Programming Language :: Python
Classifier: Programming Language :: Python :: 2
Classifier: Programming Language :: Python :: 2.7
Classifier: Programming Language :: Python :: 3
Classifier: Programming Language :: Python :: 3.4
Classifier: Programming Language :: Python :: 3.5
Classifier: Programming Language :: Python :: 3.6
Classifier: Programming Language :: Python :: 3.7
Classifier: Programming Language :: Python :: 3.8
Classifier: Development Status :: 4 - Beta
Classifier: Operating System :: OS Independent
Classifier: License :: OSI Approved :: Apache Software License
Classifier: Topic :: Multimedia :: Graphics :: Presentation
Classifier: Topic :: Text Processing :: Markup
License-File: LICENSE
Requires-Dist: MarkupSafe (==1.1.1)
Requires-Dist: Jinja2 (==2.10.1)
Requires-Dist: Markdown (==2.6.11)
Requires-Dist: Pygments (==2.2.0)
Requires-Dist: docutils (==0.14)
Requires-Dist: six (==1.11.0)
